{
	"TextAbbreviation": "lent-week-3-sunday-vespers-2-anti-3",
	"SourceAbbreviation": "breviary-antiphons",
	"FormatAs": "poetry",
	"Version": "LH",
	"Text": "Vere [*] languóres nostros ipse tulit, et dolóres nostros ipse portávit.",
	"Extra": {
		"Writing":{
			"Authors": ["Paul Prins"],
			"Step": {
				"2021-12-05": ["Peer-Review"],
				"2021-12-04": [
					"Second-Pass",
					"Initial"
				]
			},
			"Reviewers": {}
		}
	},
	"Changes": [
		"2021-12-04 - Paul Prins: Added this antiphon."
	],
	"License": "© 2000 Libreria Editrice Vaticana, Città del Vaticano"
}