{
	"TextAbbreviation": "week-2-sunday-vespers-2",
	"SourceAbbreviation": "breviary-responses",
	"FormatAs": "book",
	"Version": "LH",
	"Text": "[V] Magnus Dóminus noster, et magna virtus eius.\r\n[R] Magnus Dóminus noster, [*] et magna virtus eius.\r\n[V] Et sapiéntiæ eius non est númerus.",
	"Extra": {
		"Writing":{
			"Authors": ["Paul Prins"],
			"Step": {
				"2020-10-28": ["Peer-Review"],
				"2020-10-27": [
					"Second-Pass",
					"Initial"
				]
			},
			"Reviewers": {}
		}
	},
	"Changes": [
		"2020-10-27 - Paul Prins: Added this Response."
	],
	"License": "© 2000 Libreria Editrice Vaticana, Città del Vaticano"
}