{
	"TextAbbreviation": "concluding-ordinary-week-1-sunday",
	"SourceAbbreviation": "breviary-prayers",
	"FormatAs": "book",
	"Version": "UMB-EN",
	"Translation":{
		"Versions": ["LH"],
		"People": ["Paul Prins"]
	},
	"Text": "As the prayers of Your people rise to You, answer them, Lord, out of Your goodness. [t] With the gentleness of Your spirit, let each of us see what is to be done. [*] Give us the faith and strength to see it accomplished, through Jesus Christ.",
	"Extra": {
		"Writing":{
			"Authors": ["Paul Prins"],
			"Step": {
				"2024-01-29": ["Peer-Review"],
				"2024-01-28": [
					"Second-Pass",
					"Initial"
				]
			},
			"Reviewers": {}
		}
	},
	"Changes": [
		"2024-01-29 - Paul Prins: First translation of this prayer."
	],
	"License": "© 2024 Urban Monastics, Paris"
}