{
	"TextAbbreviation": "petitions-feast-baptism-of-the-lord",
	"SourceAbbreviation": "breviary-prayers",
	"FormatAs": "book",
	"Version": "LH",
	"Text": "[II] Redemptórem nostrum, qui baptísmum in Iordáne dignátus est a Ioánne suscípere, exorémus, dicéntes:\r\n[IR] Mitte, Dómine, Spíritum tuum super nos.\r\n[I1] Christe, serve Dei, quem Pater suscépit et in quo sibi complácuit,\r\n[I2] mitte super nos, Dómine, Spíritum tuum.\r\n[I1] Christe, elécte Dei, qui cálamum quassátum non contrivísti et linum fúmigans non exstinxísti,\r\n[I2] miserére ómnium quæréntium te in veritáte.\r\n[I1] Christe, Fili Dei, quem Pater fœ́dere novo vocávit in lucem géntium,\r\n[I2] áperi óculos cæcórum in aqua baptísmatis.\r\n[I1] Christe, hóminum salvátor, quem Pater Spíritu Sancto unxit ad ministérium salútis,\r\n[I2] duc omnes ad te vidéndum et credéndum, ut vitam ætérnam hábeant.\r\n[I1] Christe, spes nostra, qui ducis sedéntes in ténebris ad lucem salútis,\r\n[I2] fratres nostros defúnctos in regnum tuum súscipe.",
	"Changes": [
		"2022-01-09 - Paul Prins: Added these intentions."
	],
	"License": "© 2000 Libreria Editrice Vaticana, Città del Vaticano"
}