{
	"SourceAbbreviation": "salus-et-gloria",
	"Title": "Le Salut, la Gloire et la Puissance",
	"Notes": "From Revelation 19:1-7",
	"FormatAs": "poetry",
	"Version": "BMU-FR",
	"Text": "Alléluia\r\nLe salut, la gloire et la puissance à notre Dieu,[*]\r\n\tdont les jugements sont vrais et justes.\r\nAlléluia\r\n\r\nAlléluia\r\nLouez notre Dieu, tous serviteurs du Seigneur, [*]\r\n\tvous tous qui le craignez, les petit et les grand.\r\nAlléluia\r\n\r\nAlléluia\r\nLe Seigneur notre Dieu, le Tout-Puissant, règne: [*]\r\n\tréjouissons-nous et exultons et rendons gloire et hommage.\r\nAlléluia\r\n\r\nAlléluia\r\nLe mariage de l'Agneau est venu [*]\r\n\tet son épouse s'est préparée.\r\nAlléluia\r\n\r\nAlléluia\r\nHeureux ceux qui sont invités [*]\r\n\tau banquet de noces de l'Agneau.\r\nAlléluia.",
	"Extra": {
		"Passage": "Revelation 19:1-7",
		"LiturgiaeHorarum-Index": 22,
		"LiturgiaeHorarum-Cantica": "NT"
	}
}